[{"id":"942bc87e-21f6-4be2-996e-d019b34197e4","dosenNip":"199306272022031007","thumbnail":null,"namaDataset":"Data Publikasi Sinta Unila","namaPemilik":"Rahman Taufik, M.Kom","jenisDataset":"Table","linkPublikasi":"","linkRepositori":"https://drive.google.com/drive/folders/1WPGE8PVJ4e8xGuF8OaRtpZySkHX6HrNQ?usp=share_link","deskripsiDataset":"Data Publikasi Universitas Lampung yang diperoleh dari Sinta","status":"published","createdAt":"2025-12-17 08:33:24.901","updatedAt":"2025-12-17 08:37:52.845"}]